LICENSE
MANIFEST.in
setup.py
gmaps/__init__.py
gmaps/conf.py
gmaps/fields.py
gmaps/tests.py
gmaps/widgets.py
gmaps/static/gmaps/css/gmaps.css
gmaps/static/gmaps/img/gmaps-icon.png
gmaps/static/gmaps/js/.gmap.js.un~
gmaps/static/gmaps/js/.gmaps__init.js.un~
gmaps/static/gmaps/js/gmap.js
gmaps/static/gmaps/js/gmaps__init.js
gmaps/static/gmaps/js/jquery-2.1.0.min.js
gmaps/static/gmaps/select2-3.4.8/.gitignore
gmaps/static/gmaps/select2-3.4.8/LICENSE
gmaps/static/gmaps/select2-3.4.8/README.md
gmaps/static/gmaps/select2-3.4.8/bower.json
gmaps/static/gmaps/select2-3.4.8/component.json
gmaps/static/gmaps/select2-3.4.8/composer.json
gmaps/static/gmaps/select2-3.4.8/package.json
gmaps/static/gmaps/select2-3.4.8/release.sh
gmaps/static/gmaps/select2-3.4.8/select2-bootstrap.css
gmaps/static/gmaps/select2-3.4.8/select2-spinner.gif
gmaps/static/gmaps/select2-3.4.8/select2.css
gmaps/static/gmaps/select2-3.4.8/select2.jquery.json
gmaps/static/gmaps/select2-3.4.8/select2.js
gmaps/static/gmaps/select2-3.4.8/select2.min.js
gmaps/static/gmaps/select2-3.4.8/select2.png
gmaps/static/gmaps/select2-3.4.8/select2_locale_ar.js
gmaps/static/gmaps/select2-3.4.8/select2_locale_bg.js
gmaps/static/gmaps/select2-3.4.8/select2_locale_ca.js
gmaps/static/gmaps/select2-3.4.8/select2_locale_cs.js
gmaps/static/gmaps/select2-3.4.8/select2_locale_da.js
gmaps/static/gmaps/select2-3.4.8/select2_locale_de.js
gmaps/static/gmaps/select2-3.4.8/select2_locale_el.js
gmaps/static/gmaps/select2-3.4.8/select2_locale_en.js.template
gmaps/static/gmaps/select2-3.4.8/select2_locale_es.js
gmaps/static/gmaps/select2-3.4.8/select2_locale_et.js
gmaps/static/gmaps/select2-3.4.8/select2_locale_eu.js
gmaps/static/gmaps/select2-3.4.8/select2_locale_fa.js
gmaps/static/gmaps/select2-3.4.8/select2_locale_fi.js
gmaps/static/gmaps/select2-3.4.8/select2_locale_fr.js
gmaps/static/gmaps/select2-3.4.8/select2_locale_gl.js
gmaps/static/gmaps/select2-3.4.8/select2_locale_he.js
gmaps/static/gmaps/select2-3.4.8/select2_locale_hr.js
twentytab_gmaps.egg-info/PKG-INFO
twentytab_gmaps.egg-info/SOURCES.txt
twentytab_gmaps.egg-info/dependency_links.txt
twentytab_gmaps.egg-info/requires.txt
twentytab_gmaps.egg-info/top_level.txt